multihist.py
multihist-0.6.5.dist-info/LICENSE
multihist-0.6.5.dist-info/METADATA
multihist-0.6.5.dist-info/WHEEL
multihist-0.6.5.dist-info/top_level.txt
multihist-0.6.5.dist-info/RECORD
