Metadata-Version: 2.1
Name: multihist
Version: 0.6.5
Summary: Convenience wrappers around numpy histograms
Home-page: https://github.com/jelleaalbers/multihist
Author: Jelle Aalbers
Author-email: j.aalbers@uva.nl
License: MIT
Keywords: multihist,histogram
Platform: UNKNOWN
Classifier: Intended Audience :: Developers
Classifier: Development Status :: 3 - Alpha
Classifier: Programming Language :: Python
Classifier: Programming Language :: Python :: 3
Requires-Dist: numpy
